SimpleAlchemy/__init__.py
SimpleAlchemy/sqliteS.py
SSQLA-0.4.dist-info/LICENSE
SSQLA-0.4.dist-info/METADATA
SSQLA-0.4.dist-info/WHEEL
SSQLA-0.4.dist-info/top_level.txt
SSQLA-0.4.dist-info/RECORD
