Metadata-Version: 2.1
Name: SSQLA
Version: 0.4
Summary: Making SQLAlchemy simpler, because it's not
License: GNU AFFERO GENERAL PUBLIC LICENSE
Project-URL: Homepage, https://github.com/Arcader717/SAlc_Simplified
Project-URL: Bug Reports, https://github.com/Arcader717/SAlc_Simplified/issues
Project-URL: PyPi Project Page, https://pypi.org/project/SSQLA
Classifier: Development Status :: 3 - Alpha
Classifier: Intended Audience :: Developers
Classifier: Programming Language :: Python :: 3
Classifier: Programming Language :: Python :: 3.7
Classifier: Programming Language :: Python :: 3.8
Classifier: Programming Language :: Python :: 3.9
Classifier: Programming Language :: Python :: 3.10
Classifier: Programming Language :: Python :: 3.11
Classifier: Programming Language :: Python :: 3 :: Only
Requires-Python: >=3.7
License-File: LICENSE
Requires-Dist: sqlalchemy
